pidiff/__init__.py
pidiff/_impl/__init__.py
pidiff/_impl/command.py
pidiff/_impl/config.py
pidiff/_impl/pipargs.py
pidiff/_impl/schema.py
pidiff/_impl/diff/__init__.py
pidiff/_impl/diff/api.py
pidiff/_impl/diff/codes.py
pidiff/_impl/diff/diff.py
pidiff/_impl/dump/__init__.py
pidiff/_impl/dump/ast_enrich.py
pidiff/_impl/dump/command.py
pidiff/_impl/dump/dump.py
pidiff-1.7.2.dist-info/LICENSE
pidiff-1.7.2.dist-info/METADATA
pidiff-1.7.2.dist-info/WHEEL
pidiff-1.7.2.dist-info/entry_points.txt
pidiff-1.7.2.dist-info/top_level.txt
pidiff-1.7.2.dist-info/RECORD
