Metadata-Version: 2.1
Name: pidiff
Version: 1.7.2
Summary: The Python interface diff tool
Home-page: https://github.com/rohanpm/pidiff
Author: Rohan McGovern
Author-email: rohan@mcgovern.id.au
License: GNU General Public License
Project-URL: Documentation, https://rohanpm.github.io/pidiff/
Project-URL: Changelog, https://github.com/rohanpm/pidiff/blob/master/CHANGELOG.md
Requires-Python: >=3.8
License-File: LICENSE
Requires-Dist: jsonschema
Requires-Dist: virtualenv-api
Requires-Dist: semver
Requires-Dist: astroid
Requires-Dist: setuptools
